{"cameraMode":{"drawMode":0,"name":"Shaded","section":"Shading Mode"},"sceneLighting":true,"audioPlay":false,"sceneViewState":{"m_AlwaysRefresh":false,"showFog":true,"showSkybox":true,"showFlares":true,"showImageEffects":true,"showParticleSystems":true,"showVisualEffectGraphs":true,"m_FxEnabled":true},"in2DMode":false,"pivot":{"x":13.148311614990235,"y":-19.840993881225587,"z":36.764835357666019},"rotation":{"x":-0.14566931128501893,"y":0.782355010509491,"z":-0.1992114782333374,"w":-0.5722267627716065},"size":30.430587768554689,"orthographic":false}